LICENSE.txt
MANIFEST.in
README.md
WebPayloadsEncodings.py
setup.cfg
setup.py
WebPayloadsEncodings.egg-info/PKG-INFO
WebPayloadsEncodings.egg-info/SOURCES.txt
WebPayloadsEncodings.egg-info/dependency_links.txt
WebPayloadsEncodings.egg-info/entry_points.txt
WebPayloadsEncodings.egg-info/top_level.txt