Metadata-Version: 2.1
Name: WebPayloadsEncodings
Version: 0.0.2
Summary: This tool encodes Web payloads with some different encoding.
Home-page: https://github.com/mauricelambert/WebPayloadsEncodings
Author: Maurice Lambert
Author-email: mauricelambert434@gmail.com
Maintainer: Maurice Lambert
Maintainer-email: mauricelambert434@gmail.com
License: GPL-3.0 License
Project-URL: Documentation, https://mauricelambert.github.io/info/python/security/WebPayloadsEncodings.html
Project-URL: Executable, https://mauricelambert.github.io/info/python/security/WebPayloadsEncodings.pyz
Keywords: Web,Payloads,Encodings,CTF,Hacking,Security
Platform: Windows
Platform: Linux
Platform: MacOS
Classifier: Topic :: Security
Classifier: Environment :: Console
Classifier: Natural Language :: English
Classifier: Programming Language :: Python
Classifier: Programming Language :: Python :: 3.9
Classifier: Topic :: Software Development :: Build Tools
Classifier: Operating System :: MacOS
Classifier: Operating System :: POSIX :: Linux
Classifier: Operating System :: Microsoft :: Windows
Classifier: Development Status :: 5 - Production/Stable
Classifier: License :: OSI Approved :: GNU General Public License v3 (GPLv3)
Requires-Python: >=3.8
